[
    {
        "VisitID":"V00133",
        "CustomerID":"C0015",
        "Date":"2024-04-12 19:28:00",
        "ZonesVisited":"['Z005', 'Z012']",
        "Durations":"[11.21, 28.66]"
    },
    {
        "VisitID":"V00266",
        "CustomerID":"C0031",
        "Date":"2024-04-12 09:02:00",
        "ZonesVisited":"['Z015', 'Z005', 'Z002', 'Z013']",
        "Durations":"[6.81, 21.23, 28.48, 35.16]"
    },
    {
        "VisitID":"V02734",
        "CustomerID":"C0278",
        "Date":"2024-04-12 16:04:00",
        "ZonesVisited":"['Z012']",
        "Durations":"[35.82]"
    },
    {
        "VisitID":"V03032",
        "CustomerID":"C0311",
        "Date":"2024-04-12 20:24:00",
        "ZonesVisited":"['Z010', 'Z008', 'Z007', 'Z014', 'Z013']",
        "Durations":"[28.77, 10.54, 3.74, 43.23, 15.82]"
    },
    {
        "VisitID":"V04309",
        "CustomerID":"C0437",
        "Date":"2024-04-12 09:45:00",
        "ZonesVisited":"['Z015', 'Z007', 'Z002', 'Z014', 'Z005']",
        "Durations":"[20.88, 34.57, 20.71, 41.44, 3.98]"
    },
    {
        "VisitID":"V07552",
        "CustomerID":"C0761",
        "Date":"2024-04-12 18:54:00",
        "ZonesVisited":"['Z003', 'Z013']",
        "Durations":"[33.43, 18.26]"
    },
    {
        "VisitID":"V07670",
        "CustomerID":"C0770",
        "Date":"2024-04-12 18:09:00",
        "ZonesVisited":"['Z009', 'Z013', 'Z014', 'Z002', 'Z010']",
        "Durations":"[36.66, 29.76, 36.79, 32.38, 29.09]"
    },
    {
        "VisitID":"V08164",
        "CustomerID":"C0820",
        "Date":"2024-04-12 21:56:00",
        "ZonesVisited":"['Z002', 'Z006', 'Z009', 'Z001', 'Z011']",
        "Durations":"[19.16, 20.59, 24.92, 26.07, 32.08]"
    },
    {
        "VisitID":"V08853",
        "CustomerID":"C0884",
        "Date":"2024-04-12 09:53:00",
        "ZonesVisited":"['Z012', 'Z008', 'Z001', 'Z014', 'Z003']",
        "Durations":"[7.52, 3.44, 40.55, 32.76, 3.99]"
    },
    {
        "VisitID":"V09185",
        "CustomerID":"C0920",
        "Date":"2024-04-12 18:09:00",
        "ZonesVisited":"['Z012']",
        "Durations":"[15.23]"
    },
    {
        "VisitID":"V09713",
        "CustomerID":"C0977",
        "Date":"2024-04-12 16:18:00",
        "ZonesVisited":"['Z001', 'Z003', 'Z010']",
        "Durations":"[39.27, 40.2, 29.26]"
    }
]