[
    {
        "C": 15.51,
        "None": 43.12,
        "E": 30.75
    },
    {
        "D": 19.16,
        "C": 21.01,
        "None": 14.68,
        "E": 10.38
    },
    {
        "C": 31.14,
        "D": 27.11
    },
    {
        "None": 10.21,
        "B": 3.66,
        "E": 33.98,
        "A": 20.18
    },
    {
        "None": 18.259999999999998
    },
    {
        "A": 11.95
    },
    {
        "D": 23.91,
        "E": 2.7
    },
    {
        "E": 11.46,
        "A": 66.85
    },
    {
        "D": 39.88
    },
    {
        "E": 69.82000000000001,
        "C": 13.93,
        "A": 31.55,
        "B": 9.89
    },
    {
        "E": 15.84,
        "C": 28.56
    },
    {
        "A": 23.87,
        "C": 18.77
    },
    {
        "C": 3.28,
        "E": 12.58,
        "D": 17.36,
        "None": 23.73
    }
]