[
    {
        "B": 4.54,
        "None": 58.19
    },
    {
        "B": 67.25,
        "E": 33.76
    },
    {
        "A": 56.78,
        "D": 5.62
    },
    {
        "A": 22.57,
        "D": 18.97,
        "None": 17.66
    },
    {
        "D": 12.92,
        "A": 4.78,
        "C": 10.72
    },
    {
        "B": 44.14,
        "None": 13.81
    },
    {
        "D": 34.45,
        "B": 6.26
    },
    {
        "C": 62.65,
        "D": 23.27
    },
    {
        "C": 22.51
    },
    {
        "A": 4.28,
        "C": 17.52
    },
    {
        "C": 5.42,
        "None": 36.83,
        "B": 12.57
    },
    {
        "A": 57.41
    },
    {
        "A": 15.39,
        "B": 34.15,
        "E": 34.65,
        "None": 20.57,
        "C": 28.57
    },
    {
        "A": 34.17,
        "D": 30.36
    },
    {
        "None": 20.04,
        "A": 4.09,
        "B": 22.83,
        "C": 34.28,
        "E": 31.3
    },
    {
        "E": 19.91,
        "None": 2.88
    },
    {
        "E": 19.33
    },
    {
        "E": 36.91,
        "D": 28.36,
        "A": 31.75
    },
    {
        "E": 18.14,
        "D": 92.15
    }
]