[
    {
        "Age": "(38-43)",
        "Gender": "Male",
        "DateTime": "21092025 23:06:15",
        "InStoreDuration": 1881.31
    },
    {
        "Age": "(15-20)",
        "Gender": "Male",
        "DateTime": "21092025 23:06:24",
        "InStoreDuration": 16.36
    },
    {
        "Age": "(15-20)",
        "Gender": "Male",
        "DateTime": "21092025 23:06:39",
        "InStoreDuration": 44.08
    },
    {
        "Age": "(25-32)",
        "Gender": "Female",
        "DateTime": "21092025 23:06:53",
        "InStoreDuration": 0.55
    },
    {
        "Age": "(15-20)",
        "Gender": "Male",
        "DateTime": "21092025 23:07:03",
        "InStoreDuration": 0.51
    }
]